endpointlib/__init__.py
endpointlib/endpoint_factory.py
endpointlib/clients/__init__.py
endpointlib/clients/mqtt_async_client.py
endpointlib/connections/__init__.py
endpointlib/connections/connection.py
endpointlib/connections/serial_connection.py
endpointlib/connections/socket_connection.py
endpointlib/devices/__init__.py
endpointlib/devices/device.py
endpointlib/devices/serial_device.py
endpointlib/devices/socket_device.py
endpointlib/endpoints/__init__.py
endpointlib/endpoints/endpoint.py
endpointlib/endpoints/endpoint_device.py
endpointlib/endpoints/endpoint_monitor_device.py
endpointlib/helpers/__init__.py
endpointlib/helpers/loggers/__init__.py
endpointlib/helpers/loggers/async_logger_wrapper.py
endpointlib/helpers/loggers/logger_level.py
endpointlib/helpers/loggers/logger_manager.py
endpointlib/helpers/loggers/logger_settings.py
endpointlib/helpers/loggers/logger_stream.py
endpointlib/helpers/loggers/sync_logger_wrapper.py
endpointlib-0.0.12.dist-info/LICENSE
endpointlib-0.0.12.dist-info/METADATA
endpointlib-0.0.12.dist-info/WHEEL
endpointlib-0.0.12.dist-info/top_level.txt
endpointlib-0.0.12.dist-info/RECORD
