Metadata-Version: 2.1
Name: endpointlib
Version: 0.0.12
Summary: MQTT Endpoint Library
Home-page: UNKNOWN
Author: afranco
Author-email: afranco@astro.unam.mx
License: MIT
Project-URL: Source, https://github.com/afranco-astro/endpoint-lib/
Platform: UNKNOWN
Classifier: Development Status :: 4 - Beta
Classifier: Intended Audience :: Developers
Classifier: Topic :: Software Development
Classifier: Programming Language :: Python :: 3.7
Requires-Python: >=3.7
License-File: LICENSE
Requires-Dist: paho-mqtt (==1.5.1)
Requires-Dist: pyserial-asyncio (==0.5)
Requires-Dist: asyncio-mqtt (==0.10.0)
Requires-Dist: aiologger (==0.6.1)
